.gitignore
.travis.yml
AUTHORS
CHANGELOG
LICENSE
README
README.rst
genindex.html
index.html
objects.inv
search.html
searchindex.js
setup.py
docs/Makefile
docs/conf.py
docs/index.txt
docs/make.bat
docs/pushtogh
rangeset/__init__.py
rangeset.egg-info/PKG-INFO
rangeset.egg-info/SOURCES.txt
rangeset.egg-info/dependency_links.txt
rangeset.egg-info/requires.txt
rangeset.egg-info/top_level.txt
rangeset/test/__init__.py
rangeset/test/basic.txt
rangeset/test/datetime.txt
rangeset/test/mergeinfo.py
rangeset/test/test.py
sources/index.txt
static/basic.css
static/default.css
static/doctools.js
static/file.png
static/jquery.js
static/minus.png
static/plus.png
static/pygments.css
static/searchtools.js
static/sidebar.js
static/underscore.js