Metadata-Version: 2.1
Name: rangeset
Version: 0.0.15
Summary: A data structure for dealing with sets of ranges.
Home-page: https://github.com/axiak/py-rangeset/
Author: Mike Axiak
Author-email: mike@axiak.net
License: MIT
Platform: UNKNOWN
Classifier: Development Status :: 2 - Pre-Alpha
Classifier: License :: OSI Approved :: MIT License
Classifier: Operating System :: OS Independent
Classifier: Programming Language :: Python
Classifier: Topic :: Software Development :: Libraries
License-File: LICENSE
License-File: AUTHORS
